README.rst
setup.py
baguette_messaging.egg-info/PKG-INFO
baguette_messaging.egg-info/SOURCES.txt
baguette_messaging.egg-info/dependency_links.txt
baguette_messaging.egg-info/entry_points.txt
baguette_messaging.egg-info/requires.txt
baguette_messaging.egg-info/top_level.txt
farine/__init__.py
farine/discovery.py
farine/exceptions.py
farine/main.py
farine/mixins.py
farine/settings.py
farine/utils.py
farine/amqp/__init__.py
farine/amqp/consumer.py
farine/amqp/publisher.py
farine/connectors/__init__.py
farine/connectors/sql/__init__.py
farine/connectors/sql/entrypoints.py
farine/execute/__init__.py
farine/execute/method.py
farine/log/__init__.py
farine/log/logging.yaml
farine/rpc/__init__.py
farine/rpc/client.py
farine/rpc/server.py
farine/stream/__init__.py
farine/stream/sse.py
farine/tests/__init__.py
farine/tests/conftest.py
farine/tests/farine.ini
farine/tests/fixtures.py
farine/tests/models.py
farine/tests/pytest.ini
farine/tests/test_amqp.py
farine/tests/test_discovery.py
farine/tests/test_execute.py
farine/tests/test_postgres.py
farine/tests/test_rpc.py
farine/tests/test_settings.py
farine/tests/test_sse.py
farine/tests/test_utils.py
farine/tests/testfarine/__init__.py
farine/tests/testfarine/service.py