Metadata-Version: 2.1
Name: baguette-messaging
Version: 0.18
Summary: Baguette messaging framework
Home-page: https://github.com/baguette-io/baguette-messaging/
Author-email: pydavid@baguette.io
License: UNKNOWN
Keywords: micro,services,amqp,rpc,messaging
Platform: UNKNOWN
Classifier: Programming Language :: Python
Classifier: Programming Language :: Python :: 2.7
Classifier: License :: OSI Approved
Classifier: License :: OSI Approved :: GNU Lesser General Public License v3 (LGPLv3)
Classifier: Operating System :: OS Independent
Classifier: Topic :: Software Development :: Libraries :: Application Frameworks
Provides-Extra: doc
Provides-Extra: testing
Provides-Extra: postgres
